quantdle/__init__.py
quantdle/client.py
quantdle/data_downloader.py
quantdle/symbols.py
quantdle-1.0.4.dist-info/METADATA
quantdle-1.0.4.dist-info/WHEEL
quantdle-1.0.4.dist-info/licenses/LICENSE
quantdle-1.0.4.dist-info/RECORD
