Metadata-Version: 2.4
Name: quantdle
Version: 1.0.4
Summary: Official Python client library for Quantdle
License: Apache-2.0
License-File: LICENSE
Keywords: quantdle,financial-data,market-data,trading,forex,cryptocurrency
Author: Quantdle
Author-email: support@quantdle.com
Requires-Python: >=3.9,<4.0
Classifier: Development Status :: 4 - Beta
Classifier: Intended Audience :: Developers
Classifier: Intended Audience :: Financial and Insurance Industry
Classifier: License :: OSI Approved :: Apache Software License
Classifier: Operating System :: OS Independent
Classifier: Programming Language :: Python :: 3
Classifier: Programming Language :: Python :: 3.9
Classifier: Programming Language :: Python :: 3.10
Classifier: Programming Language :: Python :: 3.11
Classifier: Programming Language :: Python :: 3.12
Classifier: Programming Language :: Python :: 3.13
Classifier: Programming Language :: Python :: 3.14
Classifier: Topic :: Office/Business :: Financial :: Investment
Classifier: Topic :: Software Development :: Libraries :: Python Modules
Provides-Extra: polars
Requires-Dist: certifi
Requires-Dist: pandas (>=1.3.0)
Requires-Dist: polars (>=0.16.0) ; extra == "polars"
Requires-Dist: python-dateutil (>=2.8.0)
Requires-Dist: requests (>=2.25.0)
Requires-Dist: tqdm (>=4.60.0)
Requires-Dist: urllib3 (>=1.26.0)
Project-URL: Bug Tracker, https://github.com/quantdle/quantdle-python/issues
Project-URL: Documentation, https://github.com/quantdle/quantdle-python#readme
Project-URL: Homepage, https://quantdle.com/
Project-URL: Repository, https://github.com/quantdle/quantdle-python
